crudini_simple/__init__.py
crudini_simple/__main__.py
crudini_simple/cli.py
crudini_simple/core.py
crudini_simple-0.1.1.dist-info/METADATA
crudini_simple-0.1.1.dist-info/WHEEL
crudini_simple-0.1.1.dist-info/entry_points.txt
crudini_simple-0.1.1.dist-info/top_level.txt
crudini_simple-0.1.1.dist-info/RECORD
